{"month": "10", "state": "CA", "station": "KEIB", "content": "Out of eagerness to show a pattern up such behavior\nMayor told al magazines and her recollection of the Thomas hearings and James yeah so having watched this before I knew that key issues would be whether the judge Hannah pattern of similar behaviors since that helped establish was telling the truth when there's a standoff\nThere wasn't a pattern this is amazing\nShe ran uncorroborated story to illustrate a pattern\nI\nI'm almost speechless in my attempt to explain this\nThe first story that was run about Deborah Ramirez nobody could corroborate her story kept changing there was no evidence for it the New York times found that so bad they wouldn't they wouldn't allude to it much less reprint aspects of it and so Jane Mayer and Ronan Farrow run a second story\nThat isn't true just to establish a pattern in other words we're going to lie twice we're going to run a false story first that has no backup and then we're going to run a second story to show a pattern\nBecause I remember that with Clarence Thomas other women came forward it showed a pattern and it helped us persuade people at Thomas was guilty and so we wanted to show a pattern of behavior with Kavanaugh a pattern\nA beat you couldn't even substantiate uh single allegation be it from all the Ford or be it for Ramirez or from ... client\nWas her name swept Nick I mean this is a flat out admitting yeah we made up a second story well didn't use those words but we wanted to show a pattern\nSo essentially they're saying we believe we can convince people that something happen just by writing a story alleging it and of course their buddies in the left one gladly accept an allegation is fact and an act on it yeah we needed to show a pattern\nHere's here's Kennan Oklahoma City we're back to the phones great to have your er Hi\nHey it's great to be on Russia I'm not only are you all rush but but you are the lead voice of the mainstream media you should have the best staff and podcast\nOr should have the ...\nAnd ... [laughter] hey my point is ah today a with Hillary's comments that are basically liberals don't need to be civil to conservatives anymore it reminded me of a profound quote it came across ... years ago and maybe even you set it\nAh but here's the quote a society is either moving towards civility for barbarism and I see Trump trying to apply civil law and order to our society and it's apparent that the liberal left his embrace the farmers just wanted to get your thoughts\nAre ... but the question is do I do I agree that uh our society has always trending toward a barber is what what barbarism in a\nSociety barbarism or civilly were trending one where we're not in the middle of the ... eater trending towards the middle of the barbarism off the clocks\nAnd the oh it's a constant blocks and so what what what what was your question more Trump isn't it well\nIt seems as if a Republican conservatives are taking the side of civility and working\nUh you know towards the law and order or restoring it and it seems like the Democrats have just outright embraced barbarism right ah with all of their a character assassination attempts on Trump Kavanaugh anti a violent shooting\nYeah there's no there's no question about that it's an active choice I mean\nHillary Clinton's endorsing it\nYeah absolutely and uh it's it's sad to see because this is not the Democrat Party of my uh mother and father and I remember so well you know the conservatism here in Oklahoma where I live uh in fact and most of the states\nWell let me ask you this when was the Democrat Party the Democratic party ... what was it when that was all good and fine and dandy one more day then\nI think it was before the Nineteen forties\nNot all one word I Want not when what were they what were they like when the Democrats were the Democrat Party over your dad or your grandpa what what they want but I doing\n[laughter] well I'm the Democrats at at that time there they see a\nIssue was a labor laws and a win\nFor what purpose ... my ... the Democrats", "year": "2018", "show_name": "Barely Legal with Joe Escalante", "city": "Los Angeles", "day": "14"}