{"year": "2018", "station": "WABE", "show_name": "Jazz Classics with H. Johnson", "month": "10", "state": "GA", "day": "13", "content": "A Oregon places where the cost of living is lower on the housing affordability issue has hit a lot of people here are very hard\nCox John Cox a Republican or in this race is trying to play up his role as a as a home builder for many years he's a businessman from San Diego he says you know in his own experience he's seeing how expensive it it is to build new housing here\nAt the approval times can go on for years he compares you know building a a unit in Indiana you need six months versus here it can take up to Fifteen Years there's a little vague admittedly on how he plans to address that\nKnew him for his part is talking about how the state doesn't have specific objectives in timelines in place until the criticism Cox\nLeveled at him ways well you've been in office for sixteen years via where have you been on this all this time versus mayor of San Francisco and then as lieutenant governor\nTrump's looms large in this race but he's not um I you know you mentioned a whole lot in fact Koch never said then the word Trump during the debate that was held in a studio right next to us\nHe did get Trump's endorsement and they do have some alignment on particular issues like the border wall and sanctuary la\n... bought it for the California report your tips you read a little effects were talking to his dream Harris intelligence and national security reporter for the Washington Post thanks shame think social and political journalist and radio host Todd's will look back on TALK of push with our structural\nOne of these leads to an engineer a strict cheery or digital team is ... and kept referring to learn more about them and the rest of our team visit one a dot org slash staff\nOr till we meet again I'm Joshua Johnson thank you so much for listening from too many and enjoying the weekend were back in BC Monday This is one [noise]\n\nSupport for NPR comes from the station and from the doors do charitable foundation whos clinical scientists development towards support promising early career physician scientist and their research efforts to improve human health\nFrom the Annenberg Foundation committed to supporting educating and engaging communities in the United states and globally for more than twenty five years learned more at Annenberg Foundation dot org I'm from the William T grant foundation a W T grant foundation dot org\n\n... members supported Ninety point one W. A. B. E. at one time\nSupport for WABC come Trump wet iron school coding boot camp with the curriculum and career support designed to help\nStudents get jobs once they graduate applications were flat aren't Smithtown campus are now a bit more at flat iron school dot com oh\nWith your new sustaining donation of twenty dollars a month or a single contribution of two hundred and forty dollars we'd like to send you three great thank you get the ... the WABC fold away shop or two and a new WABC Seventy eighth anniversary pulled away to\nThe Turkish Tumblr has a black push on late and features and embroidered emblem of Seventy anniversary WABC logo and the Turks fold up neatly for pocket sized storage remember most from recycling services do not recycled plastic bags with the snake you guess you could say goodbye to both plastic bags in single use coffee got\nThis W. H. B. E. equal combo is yours is a new sustain or a twenty dollars per month please make your tax deductible\nDonation online that WABC dot org or called six Seventy five five three Ninety nine and thanks\n[noise]\n\n\nThat she told me just hurting indicates that we're going to do a special kind of program to you for you this evening here on the classics that's what it called classics\nTheme song done by Buddy Guy we're coming to you from WABC choice when NPR we're going to be swinging with the blues and two or two three o'clock whatever those are ... when you are ready for us to go because you get tired of it was ... like that\nJust heard Buddy Guy given us the opening scene but we always begin the program which will young lady this time was going to be a little bit unique in that the young lady doesn't usually sing the blues she's going to sing for the night she's a pop jazz singer primarily name is Peggy Peggy me with those of you who are familiar with ... you\nGet ready for something a little different from Peggy she's going to Chicago sorry but she can't pick you\n[noise]\n\nChicago and I\nChicago\nYou see and make\nYou know\nMy comment\nRainy yeah well\n\n\n[noise]\n\n\n\n\nYou know\n\nYeah me neither\n\nDidn't know what\nI was\nGoing to do but I I'm\n\nBad yeah piggy piggybacked on booze but it's hoping it's going to Chicago blues standard is done by Peggy and she made a stand up for himself you would think the blues classics and keeps you just joined us know\nGoing to get down to the nitty gritty the nitty gritty of the blue this is the classic and he would go with ... maybe ...\nMaybe hold and we'll many more years or something that you treat me this way\nBack in you know we all around\nNow oh\nGod you know male around\nAt least I mean it\n\nWe got\n\nYou met them by ... Webster we've got to love Billups I've got nothing you know you got nothing I've got less were put together and clean up this myth that those who might be listening to blues classics in case you just joined the army Johnson hosting you don't want to see too much of my income arrogant or blue during a copy\nOf thinking about myself and all that other stuff you know what I'm saying you know what I'm saying of course you know what I'm saying we've got a little bit ... money was I just wanted to make love to you Muddy Waters Monday it's yours\nAll right\nDon't want to be true\nA a\nLow\nWatch about go\nOut on Wall\nWhoa whoa\n\n\n\n\nMan\nDon't won't you\nMake up the\n\n[noise] [noise]\nWhat do you say I did you\nGo them then blue I didn't want\nMake to you I Love the dialect and I can\nBy the way you switch in wall I can see by the way you baby do I can I can\nSomething by the way you treat you may not you may you may not go to love you baby due credit oh my goodness money was a living legend me this time he's no longer with us but you can legacy lives on Iran booze glass it's especially\nWe said we do this one didn't\nYou know by about\nMe\nA even got a brain\nIs gone and let me\nBring my name is dawn\nHe defeated a\nZone or na na\nI ... crying all know the the\n... you know they\nGo on and on\nI Want to do with\nDue to never\nDon't even know I'm living in\nA long time that I have been going\nHigh heat to be on\nThe job\nThought I'm going to be the\nGuy I Know the gene\n\nHuh\n[laughter]\nHa\n\nMy mom had a job on\nMy father had to learn\nRather than going to a man I don't\nKnow what to drag nine\n... nine\nWho ... to ...\nNa na na na\nI keep right on the phone will be the\nRight to know that\nHe is going to\n... who may be really know nothing like what do they go\nOh ... ... ... yeah this is Charles Brown Charlie Brown did the same one that's saying merry Christmas baby may be you know limit that you'd ever year will get ready for this\nYou pick the temple believe me I mean we\n[noise]\n\n\nWas little\n\nGo and they can be\nThe\n[noise] [noise]\nWorks by ... ... when\nThat [noise]\n[noise] [noise]\nKnow\n\nYou know just what I'm Talking about\nThe\nRole of a\n[noise] you know\nHey\nI've got a job at a steel mill\nAnd I'm Still just like a very\nHere are proud of your y'all I went straight home\nAnd\n[noise]\n\nIt all out war\nDay and there are there [noise] [laughter] [noise]\n[noise]\n\n[noise]\n\n\n\n\n\n\n\n\n\n\n[noise]\nIn a\n\n\n\nLong\nMy dream job but you're going out\n\n\nOur five year old ...\nThis is to me oh\n\nI Love that too [noise] such a messaging they're [noise] have you ever been mistreated you know you got to you got to know what do you call that\nI've done by who my goodness Buddy Guy worked a Buddy Guy you'd call that one five ... years you've got to know what he's talking about five long yeah buddy I got here just a little more than what about you would you want to do more\nRight than we were on the same page you some more Buddy Guy from the beginning took a little bit not all a little bit just a little bit yeah uh\n\nThis is the blue\nBuddy Guy things about what the Buddhist or you know he's still around to read the book came in Atlanta so I've been here called\nThe media didn't get a whole to everyone would know\nThe next time become everyone should know this guy's something going on record and in person [noise]\nYour newcomer gets Buddy Guy\nHere and then on booze ...\nEver been mistreated [noise]\n\n\nYeah but it [laughter]\n\nThe story telling your story buddy\nLaw\nYou know what to do [noise] actually I don't\nNow\nHad the nerve to kick you out after five years working\nAbout I've got a job at a steel uh-huh [noise] I'm trying to steal is just like a play just like Chuck him beard as long as you're but her father y'all\n[noise] the rich\nAt home and you want me to have the nerve to do but I sure did\n[noise]\nEasily do that and the ... ... ...\nYou\nWho when he married got to work and bring home the do\nYour yeah [noise]\nFine how are you a wall to\n[noise]\n[noise] ...\nAlright but that's another without encore anyone else will move and but you know that was no you know this is blue glasses from nine to ... you are listening to nine point one FM W. H. B. E. R. lettuce towards when NPR streaming on the Web but the ... will do you let your friends you know we're doing musically\nAnd maybe we can have a party All right maybe a party I bought some or all star jam session let's do something like the ... about sweet home Chicago\n\nThe law for going directly ... go to Lenny Bruce than ill than ... ... we're really in ... sweet home Chicago you know ... ... or you know\nThere are ... ... ... ... that's with cultural basically comes out of the church than ... than\n... says hey here's a jazz all go do something for us as we close up this segment kept marking on these groups are going to call this one's going to a meeting and when you have to understand why it's called going to me no\nNo no\n\n\n\nThe ... and turn\n\nThey can come in\n\n\n... and can brew the\n[noise]\n[noise]\n\nYou're listening to members supported Ninety point one W. H. B. E. ...\nOver the years scholars have tried to define what jazz really is no one has come up with a definitive answer we know it's been around for over a century and it has origins here and the deep south and enjoy the freedom that no other musical genre does\nRagtime swaying Cuba bebop heart Bob when this goes all at all and all the styles I endless joined me X just as we explore jazz together every Saturday Night on jazz class starting at eight or maybe point was WABC\n[noise]\n\n\nUh\nOnce again just reminding you that you're listening to blues classic trope WABC\nAtlanta's choice\nWhen PR supported reveal ...\nWould lose classics\nSomething from so we haven't heard this particular to done by and cool but we've heard it before but this one recorded when Clinton President Clinton was in office\nAnd we thought we'd play because it's rather cruel people do they listen to what what made you sunny rude says to President Clinton during the\nIn\nAnd I'm\nDid in\nSeem like\nHaunted by\n[noise]\nHealth education as well\nBut\n[laughter]\nLike\n\n[laughter]\n\n[noise]\n\n\n\n\n\n[laughter]\n[noise]\n\n[laughter]\n[noise]\nWatched you know you're\nThe\nI didn't even hear you play\nBike [noise]\n[noise]\nLike here [noise]\n[noise] [laughter]\n\n[noise] [noise]\n\nGod\nTalking about the only road rules President Lincoln Clinton wherever that is a real funny name though\nI mean the twenties saw that it took today's age and what's going on today yeah president\nClinton done by plenty road to another Sonny Sonny Boy wins and you got the help [noise] I Can't do it all by myself [noise]\n\nDo\nCan do it all by myself\n[noise]\n\nUh [laughter]\nAnd [laughter]\n\nI'm\nA baby\nNa\n\nWhy [noise]\n\nWhy\nWell\n\n[noise]\nUh\nAnd from ... school where the joy the treatment is balanced with humility and generosity offering coed Catholic education for great seven to twelve marriage ... presents an open house Sunday December second from one to ... more at ... dot com\n\nAnd and and\nJust down there but\n\n... is\n[noise]\n\n\nGame all ... and\nJust the uh the\nWorst job did you you\nI didn't yeah about ... new Jeb has\nGo wrong\nUp and coming cream with his name is Albert ... didn't like the ... ...\nYeah that's what it does Albert ... where did I go role for about ... ...\nWelcome aboard and keeps you just joined us You're listening to the classics from ... from WABC yeah that was George when your and your whole series they jumped in the music is what counts going to be with you in two weeks in that doesn't that make sense no logical going to be with you until we all [noise]\nWhat was\nThe\nOur known for his\n\n\n\n\n\nMe\n\nI'm not like a\n\nYou you need to\nTry to be a lot\nMore ... than they\nMight have gone\nG D D O ...\nD\nO D\nMaybe\nMan\nOoh\n... maybe he\nAre native to me ... ...\nA new approach to the ...\nBelieve you've had the blues yes they do\nIt's the old fashioned real\nRight well I don't know\nAnd then the guy you know\nThey can pay and\nEven on the phone\nIs\nRinging and I\nMarried a woman on her\nBeing on the person I thought I mean right now and we\nHarvard and Raul\n[noise] [noise]\nYour part in guy right gotta bang\nBang and without\nUnique about their recording yet done by J. B. O. J. B. J. B. O. one thing the only thing I understood and there was the rhythm doo doo doo doo ... I've heard that a million times but it still sounds good doesn't sound we'd done well timed it doesn't sound ancient it's just\nA blues ... you know part of this\nAnd then I'll just do that\nAnd I understood and he said leave you love agreed to have with the rest of it I didn't understand what he was saying I mean he is truly a blues singer ... will boost thing to sing and such a way that you don't understand what they're saying but the thing was such a feeling that you do feel what they say that's a blues man maybe I'll do was his name\nCannibal ... had to go ooh baby Dylan example that you know you start out by saying I'm whoever the next Daniel ad we brother my baby's go live with all role that's all I'll just do my baby girl they would let her go wrong the rest of it\nA bunch of ... but it sounds\nGood sounds okay wow\nDid you need the ... do ... how do you love and greet ahead All right\nThis is an old standard\nAll movement and those who don't have to do it every now and move classic new but it will jak guys crime look at the tears roll down the street [noise] I'm not\nI'm not\nReally [noise]\n\n\n[noise]\n[noise]\n\n[noise] um I live in\nOne uh\n\n\n[noise]\nNo\n\n\n\n\n\n[noise]\n\n\n[noise]\n\n\n\n\nKnow\nBuddy Guy\nClass and do have the blues and that's the way in the\nRented I got the boot thanks very much buddy here from blue glass\nNow if you are in our\nFace to face and you know the ... you know this great\nNew home get\nSick in late [noise]\nWouldn't you have\nSaying [noise]\nSan Diego ... came\nKnow John lack guy and every band\nName we marched down Shabab an ax you for your hand\nWhat you're saying\nThis is Ninety point one WABC Atlanta oh\nWe know you've got a lot on your mind and once in a while things can start to where they were meant to reply to that we're on our\nMilky we're supposed to pick up oh and what about the plans you made for February thirtieth or those are not going to happen but you always know what's happening in the new because MORNING EDITION is part of your daily routine\nBut the biggest story than most important conversations are ready and waiting for you with an every day from six till ten on Ninety point one W. A. B. [laughter]\n\n\n\n\n[noise]\n\n\nWorry about the clock on the wall it looked like a no booze classic primates Jonathan I'm going to host the toy and try to do some rules for you I think you may\nEnjoy can relate to these classics from nine to ... went after him here uh WABC Atlanta choice when NPR Marshall just started in a hurry because we've got beautiful cuts were going to do for you may not going to get away from the reality of the booze though\nGoing to get as to Philips to open up for after you just heard the theme song is done by Buddy Guy does that every week but the guy was a guy Buddy Guy but then we spent the feel of going to give the festivities or a big shovel the ladies do we do that and she's a lady\nShe well she's no longer was a little music lives on the law is mentally thing on boots classic from\nTo fill up they give you a little after\n\nYeah yeah yeah yeah he\n\nYeah he\n\nDa da da da da na ... and the birds you know\nI'm I'm\n[noise] bad\nBad need baby boom\nKnow and you're the first to know who\nYeah I find is done with this lone air\nRemember\n\nThe\nTalk to you know a lot of mine he\nGet Bruce how\nYou remember opening a face [noise]\n\nMy mom I Am doing why not do um [noise]\n...\nMy my aunt doing why Ron [noise]\nLot of money by the time all\nUp and go do\n\n[noise]\n\nAnd knees\n\nAm now\n\nThe thrill is going to really go with them by bb king Bebe blues boy came up with the baby steps war you're listening to boot classes and can you just joined us a call ... voice a bb king made you stop and listen\nWhile you stick to the ballot that was something that you could relate to something you could understand something to make more than what you usually eat or to\nThe radio you're listening to the radio you're not watching what you could watch the radio to sold them so I can look at the\n... the young man that she was young man when do you play guitar when he was in his teens professionally with people like oh he was what I heard was with Jimmy with us from\nSyria is doing his thing booze ... name is Robyn for\nRobin for\nAnd you go to do for you you cut me to the bone\n\nNo but nobody\nKnows what it all began with this kind of trouble between a woman and land but you know the nature of the brain brain determine you never want to be led where again and I said at the at the ... problem\nYou could make a bomb [noise]\nWhat do you rent or the\nYou know one of them they're going to be in the way you cut me to the phone\nYou got a long way from the movies now you'll need me is misery we forget about it all this we even do you do the things you want to do that you don't want to hear the single word obviously\nBecause Mitt to the bone\nBeen tough to the bowl been been you\nKnow I met a man\nYou got to the\n\n\n\nLasted a dream that one did you uh do one day away up until you would do for a long\nShot that will be the marine but it was never meant to be in the end and you don't want to hear you saying those words up about it\nYou could be to the bone\n\nNot the bone things we\nDid a lot of made a man in the long you been to the ...\nYou know how to make a ... you know you got to the\nSame\n[noise]\n\n[noise]\n... [noise]\n\nWhy why\nRobin toward you got me to the bone that we're going back to the history of the ... when I say history will don't break them are just that the may booze what it is today have people listening people who like the gentleman come up next what are you the term gentleman loosely\nBecause sometimes if you know about the private lives of some of these you do need this will it applies to everyone I guess but somebody's got the ... there was a guy name\nOh little Walter you see a photograph of him you got cars all over the streets who battle yeah driving them around the ... circuit fighting the people who are listening to this weird but it's the truth is one of those gentlemen to the gentleman once again\nAnd I'm doing something that he says you shouldn't do that he's not going to do is those but we talk about everything I Know [noise]\n\nNo go down the road and\nThe other side and may\nBuying a\nYou know\n... to ...\nGets out on the street\nOr Joe I stopped\nTo knock down a lot\nShould get back home or\n[noise] my\n\n[noise]\n\n\n\nLittle\nI'm\n\n\nA\n\n\nMy mom\n... where am I remember all the\n\n\nThat was Muddy Waters McKinley Morgan feel is is the original name and always mentioned that at least a usually lays originally when you're McKinley Morgan feel a commercially notice Muddy Waters I wait forty one you're listening to those classics\n... you know the booze art as soon as they let you and\nI think you appreciate this one ... name is Bobby ... above ... going to talk about how things will be better\nAs soon as the weather breaks up a lot of his music we played and share with you before but we usually every now and then we come back to this stuff for those of you with us for the first time okay having said that once again the Bobby Bland as soon as the weather breaks [noise]\nAs soon as the weather brain may\n\nIn the\nMan [noise]\n\nA day [noise]\n\nAt the witness break Bobby Bland here on the news classic we also featured the work of a theme song or are these Buddy Guy we know that we try to get something oh we're singing\nYeah Buddy Guy is quite a guy he had a cameo appearance in the movies that are like\nA thing to do in Denver when you're dead check that out\nYou have a cameo park near the beginning what do you see my baby's a superstar she's a glass buy stuff but\nThat's not the tomb was a pretty no but but he knew no no go do this one\n\n\n\n\n\n\n\n\nI Do believe it's going to be my\n\nMan\n[noise]\n\n\n[noise]\n\n\n\nYou know [noise]\n[noise]\n\n[noise]\n\nYou just need to use the name of the blue [noise]\nYou're listening to members supported Ninety point one WABC Atlanta\nOn wait wait don't tell me we ask the tough questions that we take no not even from NPR's own Terry Gross is there something that you love that would surprise people to know\nHow well the opera because I surprised myself you know I like it nobody hears surprised [laughter] that'd be bringing\nThat nonsense around here we have plenty of our own join us for wait wait don't tell me the news with ... this morning a ten Ninety One W. A. B. E. [noise]\nOr\nAre once again what reminding you reminding you that you're listening to boot classics I don't know why we need to remind you of your regular listen to you know where you are on the dial your Ninety point one event\nWABC this is the latest choice way NPR's IMAX Johnson I'm my wife's choice will husband\nYeah I don't know if that makes sense as to who gives a hoot about how about some claimed was about ... about some real down home\nClarence gate Mel brown haven't heard from him in a while you used to do sometimes\nSometimes I slid [noise]\nSometimes I'll be ...\n\n\n\nThe charge gene\nA\n\n\n[noise]\n\n\n\n\nOn and on\n\n\n\nOh\n\n\n\n\n\nI didn't mean to me and my\n\nGo get me a job [noise]\nI'm calling us saying\nCan't always hear\nI ain't got no no\nSee\n\nFor the new roles on booze classics with a dead end street you also have the ... of several other too you know like in the evening baby when the sun goes down in Les McCann did that one and then that's\nWhat I Love them tobacco road but you heard tonight we're not going to get them all on sooner or later will you'll hear him he'll lose classical you have to keep that data set right they made a point when we're dreaming on the Web but WABC dot org WABC dot ORG\nThose of you will pick us up everywhere outside of Atlanta Welcome aboard glad to have you with a need to have you with this\nWouldn't be no us without you know that's a sec yeah\nI don't want to get\nSo that those of you are regulars here these things to all the ... that's what the recording all about you you have a recording so that you can hear more than ...\nAnd when you listen to booze classic sometimes you might hear something more than one like this one by brother ray retold do they reach the country and western pop jazz everything and the blues is one of the main\nFour days and he is one that he starts out almost like a boozy ... well he stuck to a like a boozy bluesy jazz piano or bluesy blues yeah was he is\nAnd then he starts singing in the evening\nI Want you to listen to the way\nHe brings its own in the evening when the sun's going down\nThere so much feeling so much\nIn it you can't get away from Ray Charles do in the evening when the sun goes down\nIn the men were\nAnd then he man we're\nKnow some of the ...\nNATO Rob a\nA vote or know what I'm saying to my dad\nNa na\nNa na\nIn the evening when the sun goes down did you hear the way race with Ruben and he said All right Mr Phil and Phil's with the trumpet player he started playing\nIt was nice and those will be a jazz musician speaking that we're going to have another musician to do the same song the one you just heard in the evening when the sun goes down but fill up by the name of ... musician by name abused that's lot teach\nThat he's going to blow the old bowl have you ever heard you hear a loud guitar see I'm Glad you don't\n... bean bean bean bean bean bean ...\nMay be me me me being being ...\nGlad guitar teacher to make sure that he uses lucky and he'd go play an instrument you very seldom hear playing to\nThe old bowl yeah if you see the old bowl but listen to how to use the peace delivers and handle the old bones seem to be with you just heard Rachel do here is due to fly pie\nAnd he's doing in the evening when the sun goes down\nHe promised my way\nPromised to play back\nPets are not me bowl alone\nTo build\nPoor\nMean that's you know\nChange the law mug gets a raw\n\nMe time outside\nLoan and then grown within Buddy Guy or booze classic July before we put this little and I mentioned something about the rhythm the something blues the uh the the rhythm really gets to me sometimes like when I first heard this gentleman in his rhythm actually got to a lot of people\nMade a name for himself with his style of is\nThe cold and his name was a boat deeply and they had to ... goal bow bitterly here it is\nFive and dime or a\nThat down and re knowledge intensive\nThat the top of it I\nLast game they\nA long time\nAll there to ...\nMake it very baby son\nTo make were invading finally\nGoing to ... at home\nAlong\nThey do and in\nTo get to go to was don't come to ...\n... ... ... the ... the dumped was to build up to I Can't say reverting rhythm\nFrom but we do today but we did the\nThat's a weird name though but he's swimming so do the ... brothers with sweet home Chicago\n\nOn\n\nJohn\n\nWe\nFrom\nSweet\n\n\nYou\nAnd\nNo no\nNo no no\nBy\nMeans\n[noise]\n\n", "city": "Atlanta"}